{
  "project_info": {
    "project_number": "711732971611",
    "firebase_url": "https://quizmaker-98e5e.firebaseio.com",
    "project_id": "quizmaker-98e5e",
    "storage_bucket": "quizmaker-98e5e.appspot.com"
  },
  "client": [
    {
      "client_info": {
        "mobilesdk_app_id": "1:711732971611:android:13272d375998f816ff577e",
        "android_client_info": {
          "package_name": "com.example.quizzler"
        }
      },
      "oauth_client": [
        {
          "client_id": "711732971611-7406cqr9t9ag7br33o4n3h8nu0kfn3d4.apps.googleusercontent.com",
          "client_type": 3
        }
      ],
      "api_key": [
        {
          "current_key": "AIzaSyCW3IacrkqTYFiCj8Op47wunKJ5wMHp4CE"
        }
      ],
      "services": {
        "appinvite_service": {
          "other_platform_oauth_client": [
            {
              "client_id": "711732971611-7406cqr9t9ag7br33o4n3h8nu0kfn3d4.apps.googleusercontent.com",
              "client_type": 3
            }
          ]
        }
      }
    }
  ],
  "configuration_version": "1"
}